Metadata-Version: 1.1
Name: rcmemoize
Version: 0.0.3
Summary: Cache anything in the current request cycle in memory for preventing duplicate method callers.
Home-page: https://github.com/baranbartu/rcmemoize
Author: Baran Bartu Demirci
Author-email: bbartu.demirci@gmail.com
License: MIT
Download-URL: https://github.com/baranbartu/rcmemoize/tarball/0.0.3
Keywords: django,memoize,memorize,cache,cached,cached property
Platform: UNKNOWN
